LICENSE
MANIFEST.in
README.md
setup.cfg
setup.py
stdeb.cfg
./ldap0/__about__.py
./ldap0/__init__.py
./ldap0/base.py
./ldap0/cache.py
./ldap0/cidict.py
./ldap0/dn.py
./ldap0/err.py
./ldap0/filter.py
./ldap0/functions.py
./ldap0/ldapobject.py
./ldap0/ldapurl.py
./ldap0/ldif.py
./ldap0/lock.py
./ldap0/modlist.py
./ldap0/msad.py
./ldap0/openldap.py
./ldap0/pw.py
./ldap0/py.typed
./ldap0/res.py
./ldap0/sasl.py
./ldap0/test.py
./ldap0/tmpl.py
./ldap0/typehints.py
./ldap0/controls/__init__.py
./ldap0/controls/deref.py
./ldap0/controls/libldap.py
./ldap0/controls/openldap.py
./ldap0/controls/pagedresults.py
./ldap0/controls/ppolicy.py
./ldap0/controls/psearch.py
./ldap0/controls/pwdpolicy.py
./ldap0/controls/readentry.py
./ldap0/controls/sessiontrack.py
./ldap0/controls/simple.py
./ldap0/controls/sss.py
./ldap0/controls/syncrepl.py
./ldap0/controls/vlv.py
./ldap0/extop/__init__.py
./ldap0/extop/cancel.py
./ldap0/extop/dds.py
./ldap0/extop/passmod.py
./ldap0/extop/whoami.py
./ldap0/schema/__init__.py
./ldap0/schema/models.py
./ldap0/schema/parse.py
./ldap0/schema/subentry.py
./ldap0/schema/util.py
_libldap0/common.c
_libldap0/common.h
_libldap0/constants.c
_libldap0/constants.h
_libldap0/errors.c
_libldap0/errors.h
_libldap0/functions.c
_libldap0/functions.h
_libldap0/ldapcontrol.c
_libldap0/ldapcontrol.h
_libldap0/ldapobject.c
_libldap0/ldapobject.h
_libldap0/libldap0module.c
_libldap0/message.c
_libldap0/message.h
_libldap0/options.c
_libldap0/options.h
ldap0.egg-info/PKG-INFO
ldap0.egg-info/SOURCES.txt
ldap0.egg-info/dependency_links.txt
ldap0.egg-info/requires.txt
ldap0.egg-info/top_level.txt
ldap0.egg-info/zip-safe
tests/__init__.py
tests/test_about.py
tests/test_base.py
tests/test_cache.py
tests/test_cext.py
tests/test_cidict.py
tests/test_controls.py
tests/test_dn.py
tests/test_extensions.py
tests/test_extop.py
tests/test_filter.py
tests/test_functions.py
tests/test_ldapobject.py
tests/test_ldapurl.py
tests/test_ldif.py
tests/test_modlist.py
tests/test_msad.py
tests/test_openldap.py
tests/test_ppolicy.py
tests/test_pw.py
tests/test_res.py
tests/test_schema_models.py
tests/test_schema_parse.py
tests/test_schema_subentry.py
